testtool/__init__.py
testtool/test.py
test_pypi_zgl-0.0.5.dist-info/METADATA
test_pypi_zgl-0.0.5.dist-info/WHEEL
test_pypi_zgl-0.0.5.dist-info/top_level.txt
test_pypi_zgl-0.0.5.dist-info/RECORD
