Metadata-Version: 2.1
Name: test-pypi-zgl
Version: 0.0.5
Summary: test-pypi
Home-page: UNKNOWN
Author: zgl
Author-email: 
License: MIT
Keywords: test-pypi
Platform: UNKNOWN
